MpesaRest/__init__.py
MpesaRest/mpesarest.py
MpesaRest-0.0.9.dist-info/LICENSE
MpesaRest-0.0.9.dist-info/METADATA
MpesaRest-0.0.9.dist-info/WHEEL
MpesaRest-0.0.9.dist-info/top_level.txt
MpesaRest-0.0.9.dist-info/RECORD
