Metadata-Version: 2.1
Name: MpesaRest
Version: 0.0.9
Summary: An interaction of the Safaricom Daraja Api with Python
Author-email: Lumuli Ken Reagan <lumulikenreagan@gmail.com>
Project-URL: Homepage, https://github.com/kenreagan/MpesaRestt
Project-URL: Bug Tracker, https://github.com/kenreagan/MpesaRest/issues
Classifier: Intended Audience :: Developers
Classifier: Programming Language :: Python
Classifier: Operating System :: OS Independent
Requires-Python: >=3.7
License-File: LICENSE
